idlealib/__init__.py
idlealib/help.py
idlea-0.0.1.dist-info/METADATA
idlea-0.0.1.dist-info/WHEEL
idlea-0.0.1.dist-info/license.txt
idlea-0.0.1.dist-info/top_level.txt
idlea-0.0.1.dist-info/RECORD
